LICENSE
MANIFEST.in
README.rst
setup.py
citations/__init__.py
citations/admin.py
citations/forms.py
citations/models.py
citations/tests.py
citations/views.py
citations/templates/reference_list.html
citations/templates/admin/imported.html
citations/templates/admin/unable_to_upload_bibtex.html
citations/templates/admin/updated_change_form.html
django_citations.egg-info/PKG-INFO
django_citations.egg-info/SOURCES.txt
django_citations.egg-info/dependency_links.txt
django_citations.egg-info/requires.txt
django_citations.egg-info/top_level.txt